{
  "1. 根据《中华人民共和国安全生产法》，生产经营单位的主要负责人对本单位的安全生产工作（）。 (单选题)\n负次要责任\n负全面责任\n负部分责任\n不负责任": "B",
  "2. 以下哪项不属于施工单位的安全责任？ (单选题)\n制定安全生产规章制度\n提供劳动防护用品\n为从业人员购买商业保险\n组织安全生产教育培训": "C",
  "3. 生产经营单位的安全生产费用应由（ ）负责提取和使用。 (单选题)\n企业主要负责人\n财务部门\n安全生产管理部门\n人力资源部门": "A",
  "4. 以下哪项不属于施工单位的安全管理职责？ (单选题)\n组织安全生产教育培训\n制定安全生产规章制度\n提供劳动防护用品\n审批施工图纸": "D",
  "5. 根据《通信建设工程安全生产管理规定》，施工单位应为从业人员购买（ ）。 (单选题)\n工伤保险\n意外伤害保险\n商业保险\n无需购买保险": "A",
  "6. 根据《通信建设工程安全生产管理规定》，通信建设工程安全生产工作应坚持的方针是？ (单选题)\n安全第一、预防为主、综合治理\n预防为主、防消结合\n安全生产、人人有责\n质量第一、安全第二": "A",
  "7. 发生通信建设工程生产安全事故后，单位负责人应在多长时间内报告？ (单选题)\n2小时内\n1小时内\n12小时内\n24小时内": "B",
  "8. 在有限空间作业时，必须严格实行的制度是？ (单选题)\n作业审批制度\n安全培训制度\n定期检查制度\n无需审批": "A",
  "9. 根据文件2，人孔作业时必须配备的检测仪器是？ (单选题)\n气体检测仪\n湿度检测仪\n温度检测仪\n压力检测仪": "A",
  "10. 在电力设施附近作业时，作业人员必须保持的最小安全距离（35KV以下）是？ (单选题)\n1米\n2.5米\n3米\n4米": "B",
  "11. 高处作业时，安全带的正确使用方法是？ (单选题)\n低挂高用\n高挂低用\n平挂平用\n不需要使用": "B",
  "12. 在通信机房内，施工人员应如何处理金属物品？ (单选题)\n随意放置\n统一放置在规定区域\n带入机房\n无需处理": "B",
  "13. 根据文件2，高速公路施工时，安全警示标志应设置在作业点来车方向多远处？ (单选题)\n100米\n500米\n1000米\n2000米": "C",
  "14. 在吊线周围有电力线时，严禁使用吊板作业的距离是？ (单选题)\n50cm以内\n70cm以内\n100cm以内\n150cm以内": "B",
  "15. 根据《判定标准》，施工单位的项目负责人必须持有的证书是？ (单选题)\n安全生产考核合格证书\n职业资格证书\n技术等级证书\n无需证书": "A",
  "16. 根据文件2，光缆敷设时，吹缆设备的气压不得超过硅芯管允许压力的范围，正确的做法是？ (单选题)\n使用高压气管，压力不超过允许范围\n使用低压气管\n无需控制压力\n直接使用高压气泵": "A",
  "17. 在雷电天气下，是否允许进行基站天馈线安装作业？ (单选题)\n允许\n不允许\n视情况而定\n无需特别注意": "B",
  "18. 根据文件1，通信建设工程安全生产费用的提取和使用管理应执行的规定是？ (单选题)\n财政部、应急管理部相关规定\n企业自定标准\n行业协会规定\n无需管理": "A",
  "19. 在拆除电杆时，正确的操作顺序是？ (单选题)\n先拆移杆上线缆，再拆除拉线，最后拆除电杆\n先拆除电杆，再拆移线缆\n同时拆除线缆和电杆\n无需特定顺序": "A",
  "20. 根据文件2，以下哪项是高速公路施工时必须佩戴的装备？ (单选题)\n反光背心\n普通工作服\n雨衣\n无需特殊装备": "A",
  "21. 在通信机房内进行动火作业时，必须事先办理的手续是？ (单选题)\n动火证\n施工许可证\n安全生产许可证\n无需手续": "A",
  "22. 根据文件3，重大事故隐患的判定依据是什么？ (单选题)\n安全生产法律法规及强制性标准\n企业内部规定\n行业惯例\n无需依据": "A",
  "23. 在进行高处作业时，以下哪项是正确的安全措施？ (单选题)\n系好安全带并高挂低用\n仅佩戴安全帽\n无需防护措施\n穿拖鞋作业": "A",
  "24. 根据文件2，以下哪项是人孔作业时必须配备的个人防护装备？ (单选题)\n防毒面具\n普通口罩\n防护眼镜\n无需防护": "A",
  "25. 在通信机房内，临时用电必须做好哪些保护措施？ (单选题)\n接地和绝缘保护\n仅接地保护\n仅绝缘保护\n无需保护": "A",
  "26. 根据文件1，施工单位的安全生产教育培训制度要求每年至少进行几次培训？ (单选题)\n一次\n两次\n三次\n四次": "A",
  "27. 在进行吊装作业时，以下哪项是正确的做法？ (单选题)\n使用磨损的吊装绳索\n定期检查吊装设备\n无需检查\n超载使用": "B",
  "28. 根据文件2，以下哪项是高速公路施工时必须遵守的规定？ (单选题)\n在雾天进行施工\n严格按照批准的施工方案进行施工\n随意变更施工时间\n无需设置安全标志": "B",
  "29. 在通信机房内，以下哪项行为是被禁止的？ (单选题)\n吸烟\n佩戴安全帽\n穿戴绝缘鞋\n使用防静电手腕带": "A",
  "30. 根据文件3，以下哪项不属于重大事故隐患的情形？ (单选题)\n特种作业人员未持证上岗\n施工现场设置安全警示标识\n未制定生产安全事故现场处置方案\n出现自然灾害预警强行施工": "B",
  "31. 在进行登高作业时，以下哪项是正确的做法？ (单选题)\n使用安全带并高挂低用\n穿硬底鞋\n在杆上抛掷工具\n无需检查登高工具": "A",
  "32. 根据文件2，以下哪项是移动基站天馈线安装作业时必须配备的装备？ (单选题)\n防坠落自锁装置\n普通安全带\n无需防护装备\n普通工作鞋": "A",
  "33. 在通信机房内，以下哪项是正确的操作？ (单选题)\n在机柜顶上放置工具\n及时清理施工产生的易燃材料\n使用砂轮切割机\n随意挪动消防设施": "B",
  "34. 根据文件1，建设单位应在工程开工后多长时间内支付至少50%的安全生产费用？ (单选题)\n一个月内\n两个月内\n三个月内\n开工当日": "A",
  "35. 在进行有限空间作业时，以下哪项是正确的做法？ (单选题)\n作业现场设置专人监护\n作业人员单独操作\n无需通风\n作业完成后立即封闭空间": "A",
  "36. 根据文件2，以下哪项是直埋光缆敷设时必须采取的措施？ (单选题)\n调查地下原有管线分布\n直接开挖\n使用重型机械\n无需调查": "A",
  "37. 根据文件3，以下哪项属于重大事故隐患的情形？ (单选题)\n施工单位制定了现场处置方案\n未对特种作业人员进行安全技术交底\n建设单位将工程发包给具备资质的施工单位\n施工现场设置了安全警示标识": "B",
  "38. 在通信机房内进行设备割接时，以下哪项是正确的做法？ (单选题)\n由未经培训的人员操作\n作业人员必须持有特种作业操作证书\n使用不具备阻燃功能的电缆\n无需绝缘遮挡": "B",
  "39. 根据文件2，以下哪项是电梯井道作业时必须采取的措施？ (单选题)\n悬挂“正在施工”的安全警示标志\n无需防护直接进入井道\n在井道内上下同时作业\n无需检查井道环境": "A",
  "40. 在进行高处作业时，以下哪项是正确的做法？ (单选题)\n在浓雾天气作业\n系好安全带并高挂低用\n使用不合格的登高工具\n无需佩戴安全帽": "B",
  "41. 《安全生产法》规定，生产经营单位主要负责人应组织制定并实施本单位（ ） (单选题)\n安全生产规章制度\n年度生产计划\n设备采购方案\n员工福利政策": "A",
  "42. 通信工程总承包单位依法将专业工程分包时，安全生产责任由（ ）承担 (单选题)\n总承包单位\n分包单位\n建设单位和总包单位连带\n总包与分包单位共同": "D",
  "43. 根据《生产安全事故报告和调查处理条例》，重大事故是指造成（ ） (单选题)\n3人以下死亡\n3-10人死亡\n10-30人死亡\n30人以上死亡": "C",
  "44. 安全生产许可证的有效期为（ ） (单选题)\n1年\n2年\n3年\n5年": "C",
  "45. 《通信建设工程安全生产管理规定》要求安全技术交底应在（ ）进行 (单选题)\n开工前\n每周例会\n发生事故后\n项目验收阶段": "A",
  "46. 特种作业人员未取得操作资格证书上岗作业的，最高可处罚（ ） (单选题)\n1万元以下\n5万元以下\n10万元以下\n20万元以下": "B",
  "47. 根据《建设工程安全生产管理条例》，专职安全管理人员配置标准是（ ） (单选题)\n每5000万合同额配1人\n每专业分包配1人\n施工人员3%以上\n建筑面积1万㎡配1人": "A",
  "48. 生产安全事故发生后，单位负责人应在（ ）内向县级以上政府报告 (单选题)\n半小时\n1小时\n2小时\n24小时": "B",
  "49. 《安全生产事故隐患排查治理暂行规定》要求隐患整改方案应当包括（ ） (单选题)\n整改措施、责任、资金、时限\n事故责任认定报告\n员工处罚决定\n保险理赔方案": "A",
  "50. 通信工程应急预案演练频次要求至少（ ） (单选题)\n每季度1次\n每半年1次\n每年1次\n每两年1次": "B",
  "51. 《危险性较大的分部分项工程安全管理规定》中要求专家论证的工程是（ ） (单选题)\n开挖深度3m的基坑\n起重量200kN的起重设备\n搭设高度50m的落地架\n采用常规工艺的管道工程": "C",
  "52. 从业人员发现直接危及人身安全的紧急情况时，依法享有（ ） (单选题)\n继续作业权\n拒绝作业权\n检举控告权\n建议权": "B",
  "53. 《建筑施工企业安全生产管理机构设置标准》规定，企业安全部门是（ ） (单选题)\n独立部门\n工程部下属科室\n综合办公室兼管\n财务部代管": "A",
  "54. 违反《安全生产法》导致发生较大事故的，对主要负责人处上一年年收入（ ） (单选题)\n0.3\n0.4\n0.6\n0.8": "C",
  "55. 建设单位在编制工程概算时，应确定（ ） (单选题)\n安全生产措施费用\n工程预备费\n项目管理费\n质量保证金": "A",
  "56. 《特种设备安全法》规定，电梯的维护保养应当由（ ）进行 (单选题)\n使用单位\n制造单位\n第三方检测机构\n取得许可的安装单位": "D",
  "57. 工伤保险费的缴纳主体是（ ） (单选题)\n建设单位\n施工总承包单位\n从业人员个人\n用人单位": "D",
  "58. 《生产安全事故应急条例》规定应急救援队伍应（ ）开展训练 (单选题)\n每月\n每季度\n每半年\n每年": "B",
  "59. 对重大危险源应登记建档并定期检测评估，依据的法律是（ ） (单选题)\n劳动法\n安全生产法\n建筑法\n招标投标法": "B",
  "60. 通信工程施工企业应至少（ ）组织一次综合应急预案演练 (单选题)\n每季度\n每半年\n每年\n每两年": "C",
  "61. 安全风险分级管控中的\"四色\"标识对应风险等级正确的是？ (单选题)\n红-重大 橙-较大 黄-一般 蓝-低\n红-特大 橙-重大 黄-较大 蓝-一般\n红-重大 黄-较大 蓝-一般 绿-低\n橙-重大 黄-较大 蓝-一般 绿-低": "A",
  "62. 安全技术交底必须由（ ）签字确认 (单选题)\n交底人与被交底人\n项目经理与安全员\n交底人、被交底人、监理\n施工班组长与作业人员": "C",
  "63. 有限空间作业前气体检测的有效时长是？ (单选题)\n作业前1小时内\n作业前30分钟内\n连续监测即可\n作业前24小时内": "B",
  "64. 起重吊装作业中钢丝绳的安全系数应不小于？ (单选题)\n4\n5\n6\n8": "C",
  "65. 施工现场灭火器检查的正确周期是？ (单选题)\n每周\n每月\n每季度\n每年": "B",
  "66. 雨季施工时基坑支护结构位移监测频率应为？ (单选题)\n每天1次\n每周2次\n每3天1次\n出现险情时监测": "A",
  "67. 安全标志中红色代表的含义是？ (单选题)\n禁止\n警告\n指令\n提示": "A",
  "68. 漏电保护器的定期测试周期应为？ (单选题)\n每周\n每月\n每季度\n每年": "B",
  "69. 安全帽的有效使用期限最长不超过？ (单选题)\n24个月\n30个月\n36个月\n48个月": "B",
  "70. 三级安全教育体系具体指？ (单选题)\n公司-部门-班组\n总包-分包-班组\n公司-项目-班组\n建设-施工-监理": "C",
  "71. 高处作业吊篮安全锁校验周期是？ (单选题)\n1个月\n3个月\n6个月\n12个月": "C",
  "72. 临时用电系统应采用的配电保护方式是？ (单选题)\n三级配电二级保护\n三级配电三级保护\n二级配电一级保护\n一级配电集中保护": "A",
  "73. 焊接作业时氧气瓶与乙炔瓶的最小安全距离是？ (单选题)\n3米\n5米\n8米\n10米": "B",
  "74. 危险性较大的分部分项工程专项方案审批流程是？ (单选题)\n项目技术负责人审批\n企业技术负责人审批\n总监理工程师审批\n专家论证后总监审批": "D",
  "75. 安全通道的防护棚搭设宽度应大于通道两侧各（ ） (单选题)\n0.5m\n1m\n1.5m\n2m": "A",
  "76. 应急预案的核心组成部分是？ (单选题)\n应急组织体系\n事故风险评估\n应急响应程序\n后期处置措施": "C",
  "77. 隐患整改\"五定\"原则不包括？ (单选题)\n定整改措施\n定整改资金\n定整改效果\n定整改复查人": "C",
  "78. 事故调查处理的\"四不放过\"原则中首要的是？ (单选题)\n责任人未处理不放过\n群众未受教育不放过\n事故原因未查清不放过\n整改措施未落实不放过": "C",
  "79. 安全技术措施计划编制的优先顺序是？ (单选题)\n防护-隔离-警告-个人防护\n消除-替代-工程控制-个人防护\n隔离-警告-培训-个人防护\n应急-防护-检查-处罚": "B",
  "80. 安全带静负荷试验标准是（ ）分钟 (单选题)\n3\n5\n10\n15": "B",
  "81. 建设单位在招标文件中必须明确的安全管理要求是？ (单选题)\n安全生产费用不可竞争性\n允许分包单位资质后审\n接受安全文明施工费下浮\n允许压缩合理工期": "A",
  "82. 项目开工前建设单位应组织（ ）进行安全条件审查 (单选题)\n设计单位\n施工单位\n监理单位和专家\n政府监管部门": "C",
  "83. 建设单位项目负责人每月带班检查不得少于（ ） (单选题)\n1次\n2次\n工程量的25%\n项目关键节点": "A",
  "84. 建设单位安全生产费用使用监管重点应是？ (单选题)\n费用足额支付\n是否专款专用\n费用决算金额\n发票合规性": "B",
  "85. 施工合同应明确超过（ ）的危大工程需专家论证 (单选题)\n一定规模\n合同金额10%\n工期30天以上\n涉及特种设备": "A",
  "86. 建设单位在项目安全管理中的核心职责是？ (单选题)\n直接指挥施工\n监督检查参建方履责\n编制应急预案\n组织安全培训": "B",
  "87. 竣工验收阶段需核查的安全生产资料是？ (单选题)\n特种作业证书\n安全日志\n安全评价报告\n风险抵押金缴纳凭证": "C",
  "88. 建设单位发现施工单位违规降低安全标准时应采取（ ） (单选题)\n扣除工程款\n签发停工令\n向安监部门报告\n要求监理处罚": "B",
  "89. 建设单位项目安全考核指标应包含（ ） (单选题)\n事故起数\n安全文明工地创建\n监理通知单数量\n应急演练次数": "B",
  "90. 项目安全风险抵押金应在（ ）阶段返还 (单选题)\n主体完工\n竣工验收备案\n质保期结束\n结算审计完成": "C",
  "91. 建设单位安全生产费用支付凭证保存期限至少（ ） (单选题)\n2年\n3年\n5年\n永久保存": "C",
  "92. 项目安全生产协议必须明确（ ） (单选题)\n事故赔偿标准\n各方管理边界\n安全处罚细则\n保险理赔流程": "B",
  "93. 建设单位对监理单位安全监督的考核重点是？ (单选题)\n监理日志完整性\n安全隐患整改闭合率\n监理人员出勤率\n监理月报及时性": "B",
  "94. 项目安全奖惩制度应经（ ）审议通过 (单选题)\n建设单位安委会\n施工项目部\n监理例会\n政府监管部门": "A",
  "95. 建设单位应组织专家论证的情形是？ (单选题)\n深基坑设计变更\n施工进度滞后30%\n安全费用超支\n监理人员配备不足": "A",
  "96. 项目安全生产标准化自评应（ ）开展 (单选题)\n每月\n每季度\n每年\n竣工前": "D",
  "97. 建设单位安全文明施工费支付比例不得低于（ ） (单选题)\n0.5\n0.6\n0.8\n1": "C",
  "98. 项目安全责任书签订对象应包含（ ） (单选题)\n材料供应商\n设计负责人\n分包单位\n检测机构": "C",
  "99. 建设单位安全监督周报必须包含（ ） (单选题)\n质量缺陷统计\n重大风险管控\n进度对比分析\n设计变更汇总": "B",
  "100. 项目安全绩效考核中占比最大的指标是？ (单选题)\n安全培训覆盖率\n隐患整改及时率\n事故经济损失\n安全创新成果": "B",
  "101. 安全观察卡（STOP卡）制度主要用于强化（ ） (单选题)\n领导带班检查\n作业人员互查\n第三方评估\n政府飞行检查": "B",
  "102. HAZOP分析法的核心是识别（ ） (单选题)\n设备故障模式\n工艺参数偏差\n人员操作失误\n环境变化影响": "B",
  "103. JSA分析中需优先控制的风险等级是（ ） (单选题)\nLEC法D级\nLEC法E级\n风险矩阵红色区\n风险矩阵橙色区": "C",
  "104. 5G基站AAU设备安装特有的安全风险是（ ） (单选题)\n电磁辐射超标\n抱杆承重不足\n光缆弯曲半径小\n电源线反接": "A",
  "105. 受限空间救援演练必须包含（ ） (单选题)\n三脚架救援\n自给式呼吸器使用\n心肺复苏操作\n应急照明布置": "B",
  "106. 安全文化成熟度评价指标不包括（ ） (单选题)\n员工主动报告隐患率\n安全投入占产值比\n管理层安全承诺可见度\n事故统计指标": "D",
  "107. 人机工程学在通信工程的应用重点是（ ） (单选题)\n优化设备颜色标识\n调整作业台高度\n增加安全警示标语\n缩短作业时间段": "B",
  "108. 危险废物贮存场所警示标识应使用（ ）色 (单选题)\n红\n黄\n蓝\n黑": "B",
  "109. 手持式光时域反射仪（OTDR）操作时需防范（ ） (单选题)\n激光辐射\n高压电击\n化学气体\n机械卷入": "A",
  "110. 安全预警系统中黄色警报对应（ ）级响应 (单选题)\nⅠ\nⅡ\nⅢ\nⅣ": "B",
  "111. 防雷接地装置接地电阻值应≤（ ）Ω (单选题)\n4\n10\n20\n30": "A",
  "112. 光缆熔接作业温度应控制在（ ）℃以下 (单选题)\n15\n25\n35\n45": "B",
  "113. 安全行为指数（SBI）考核的基准值是（ ） (单选题)\n0.8\n0.9\n1\n1.2": "C",
  "114. 噪声作业场所应设置的警示标识是（ ） (单选题)\n必须戴护耳器\n当心噪声\n噪声有害\n禁止喧哗": "B",
  "115. 剩余电流动作保护器的动作电流值应≤（ ）mA (单选题)\n10\n30\n50\n100": "B",
  "116. 安全绩效指标中\"隐患整改率\"的计算公式是（ ） (单选题)\n已整改数/发现总数×100%\n按期整改数/应整改数×100%\n重复隐患数/总隐患数×100%\n重大隐患数/总隐患数×100%": "B",
  "117. 设备机架安装时底部绝缘垫片的作用是（ ） (单选题)\n防静电\n防潮\n防震动\n防倾斜": "A",
  "118. 安全委员会季度会议必须审议的内容是（ ） (单选题)\n事故调查报告\n下季度安全预算\n安全目标完成度\n新工艺风险评估": "C",
  "119. 灭火器达到报废年限的是（ ） (单选题)\n水基型4年\n干粉8年\n二氧化碳12年\n洁净气体10年": "C",
  "120. 安全信息化系统中GIS技术主要用于（ ） (单选题)\n隐患定位\n培训记录管理\n应急资源调度\n作业票审批": "A",
  "121. 新《安全生产法》规定的\"三管三必须\"原则是指（ ） (单选题)\n管行业、管业务、管生产经营\n管人、管事、管设备\n管风险、管隐患、管事故\n管培训、管检查、管处罚": "A",
  "122. 危险作业现场监护人员必须持有（ ） (单选题)\n安全员资格证\n注册安全工程师证\n特种作业操作证\n现场监护专项培训证": "D",
  "123. 生产经营单位事故隐患排查应至少（ ）开展一次 (单选题)\n每日\n每周\n每月\n每季度": "C",
  "124. 重大危险源登记建档后应向（ ）备案 (单选题)\n应急管理部门\n行业主管部门\n技术监督部门\n公安消防部门": "A",
  "125. 安全评价机构资质等级分为（ ） (单选题)\n甲、乙两级\n一、二、三级\n国家、省级、市级\n综合、专业两类": "A",
  "126. 工伤保险条例规定工伤认定申请时限是（ ） (单选题)\n事故发生后15日内\n事故发生后30日内\n诊断鉴定后15日内\n诊断鉴定后30日内": "D",
  "127. 对发生重大事故的企业实施\"双罚制\"指（ ） (单选题)\n罚企业+罚负责人\n罚企业+罚行业\n行政罚+刑事罚\n经济罚+信用罚": "A",
  "128. 应急预案修订条件不包括（ ） (单选题)\n生产工艺变化\n应急演练发现问题\n机构人员调整\n法律法规更新": "C",
  "129. 《刑法》修正案规定强令他人冒险作业最高可处（ ） (单选题)\n3年有期徒刑\n5年有期徒刑\n7年有期徒刑\n10年有期徒刑": "C",
  "130. 高危行业安全总监应具备（ ）资格 (单选题)\n注册安全工程师\n一级建造师\n高级工程师\n企业负责人安全培训合格": "A",
  "131. 安全信用惩戒措施包括（ ） (单选题)\n限制招投标\n降低资质等级\n吊销营业执照\n没收违法所得": "A",
  "132. 新安法规定全员安全责任制需公示（ ） (单选题)\n企业负责人职责\n岗位安全责任清单\n安全生产承诺书\n安全考核指标": "B",
  "133. 安全培训时间计入工作时间的规定出自（ ） (单选题)\n劳动法\n安全生产法\n职业教育法\n劳动合同法": "B",
  "134. 建设工程安全费用提取标准中通信工程为（ ） (单选题)\n0.015\n0.02\n0.025\n0.03": "A",
  "135. 特别重大事故调查组组长由（ ）担任 (单选题)\n国务院指定人员\n省级政府负责人\n应急管理部部长\n行业主管部门领导": "A",
  "136. 安全生产举报奖励最高可达（ ） (单选题)\n10万元\n30万元\n50万元\n100万元": "B",
  "137. 安全标准化二级企业评审需满足（ ） (单选题)\n三年无亡人事故\n两年无重伤事故\n一年无重大隐患\n通过第三方审计": "A",
  "138. 消防法规定重点单位应（ ）开展消防演练 (单选题)\n每月\n每季度\n每半年\n每年": "C",
  "139. 安全预评价报告有效期自（ ）起计算 (单选题)\n编制完成日\n评审通过日\n项目开工日\n备案登记日": "B",
  "140. 危大工程验收人员必须包含（ ） (单选题)\n建设单位代表\n监理工程师\n专项方案编制人\n专家库成员": "C\n多选题",
  "1. 根据《中华人民共和国安全生产法》，生产经营单位的主要负责人对本单位的安全生产工作负有以下哪些职责？ (多选题)\n建立健全安全生产责任制\n组织制定安全生产规章制度\n保证安全生产投入的有效实施\n组织制定并实施生产安全事故应急救援预案": "A/B/C/D",
  "2. 施工单位在施工现场应采取哪些安全措施？ (多选题)\n设置明显的安全警示标志\n配备必要的消防器材\n施工人员必须佩戴安全帽\n施工现场应有专人负责安全监督": "A/B/C/D",
  "3. 根据《通信建设工程安全生产管理规定》，施工单位应为从业人员提供哪些保障？ (多选题)\n劳动防护用品\n安全生产培训\n工伤保险\n意外伤害保险": "A/B/C/D",
  "4. 以下哪些属于施工现场的安全管理要求？ (多选题)\n施工现场应设置围挡\n施工现场应有专人负责安全监督\n施工人员必须佩戴安全帽\n施工现场应配备必要的消防器材": "A/B/C/D",
  "5. 根据《通信工程施工企业主要负责人项目负责人和专职安全生产管理人员安全生产考核管理规定》，施工单位的项目负责人应具备哪些能力？ (多选题)\n安全生产知识和管理能力\n组织实施安全生产规章制度的能力\n应急救援指挥能力\n安全隐患排查治理能力": "A/B/C/D",
  "6. 根据《通信建设工程安全生产管理规定》，施工单位应定期组织哪些活动？ (多选题)\n安全生产教育培训\n应急演练\n安全生产检查\n安全生产考核": "A/B/C/D",
  "7. 根据《通信建设工程安全生产管理规定》，施工单位应建立哪些制度？ (多选题)\n安全生产责任制\n安全生产教育培训制度\n安全生产检查制度\n安全生产考核制度": "A/B/C/D",
  "8. 施工单位在施工现场应如何处理易燃易爆物品？ (多选题)\n存放在指定的安全区域\n远离火源\n设置明显的安全警示标志\n专人负责管理": "A/B/C/D",
  "9. 根据《通信建设工程安全生产管理规定》，施工单位应为从业人员购买哪些保险？ (多选题)\n工伤保险\n意外伤害保险\n商业保险\n无需购买保险": "A/B",
  "10. 施工单位在施工现场应如何处理动火作业的安全问题？ (多选题)\n办理动火许可证并采取防火措施\n设置防火隔离带\n配备灭火器材\n动火作业必须有专人监护": "A/B/C/D",
  "11. 根据《通信建设工程安全生产管理规定》，施工单位应如何处理特种设备的安全问题？ (多选题)\n特种设备必须定期检验\n特种设备操作人员必须持证上岗\n特种设备必须有专人负责管理\n特种设备必须有应急救援预案": "A/B/C/D",
  "12. 根据《通信建设工程安全生产管理规定》，施工单位应如何处理高处作业的安全问题？ (多选题)\n设置安全网和防护栏\n使用合格的脚手架\n施工人员必须佩戴安全带\n高处作业必须有专人监护": "A/B/C/D",
  "13. 施工单位在施工现场应如何处理有限空间作业的安全问题？ (多选题)\n通风和检测气体\n设置安全警示标志\n有限空间作业必须有专人监护\n有限空间作业必须配备应急救援设备": "A/B/C/D",
  "14. 施工单位在施工现场应如何处理临时设施的安全问题？ (多选题)\n设置安全警示标志\n临时设施必须稳固\n临时设施必须有防风、防雨措施\n临时设施必须有专人负责检查": "A/B/C/D",
  "15. 根据《通信建设工程安全生产管理规定》，施工单位应为从业人员提供哪些劳动防护用品？ (多选题)\n安全帽\n安全带\n防护鞋\n防护手套": "A/B/C/D",
  "16. 根据《通信建设工程安全生产管理规定》，施工单位应如何处理施工现场的用电安全问题？ (多选题)\n使用漏电保护装置\n电气设备必须接地\n电气设备必须有短路保护\n电气设备必须有专人负责管理": "A/B/C/D",
  "17. 根据《通信建设工程安全生产管理规定》，施工单位应如何处理施工现场的消防安全问题？ (多选题)\n配备必要的消防器材\n设置消防通道\n制定消防应急预案\n定期组织消防演练": "A/B/C/D",
  "18. 施工单位在施工现场应如何处理临时用电的安全问题？ (多选题)\n使用漏电保护装置\n电气设备必须接地\n电气设备必须有短路保护\n电气设备必须有专人负责管理": "A/B/C/D",
  "19. 根据《通信建设工程安全生产管理规定》，施工单位应如何处理施工现场的安全问题？ (多选题)\n设置安全警示标志\n配备必要的消防器材\n施工人员必须佩戴安全帽\n施工现场应有专人负责安全监督": "A/B/C/D",
  "20. 根据《通信建设工程安全生产管理规定》，施工单位应为从业人员提供哪些培训？ (多选题)\n安全生产法律法规\n安全操作规程\n事故应急处理措施\n职业健康知识": "A/B/C/D",
  "21. 施工单位在施工现场应如何处理高处作业的安全问题？ (多选题)\n设置安全网和防护栏\n使用合格的脚手架\n施工人员必须佩戴安全带\n高处作业必须有专人监护": "A/B/C/D",
  "22. 根据《通信建设工程安全生产管理规定》，施工单位的安全生产责任包括哪些？ (多选题)\n设置安全生产管理机构\n配备专职安全生产管理人员\n制定生产安全事故现场处置方案\n每年组织一次应急演练": "A,B,C,D",
  "23. 根据文件2，以下哪些作业场景属于高危险源？ (多选题)\n架空线路作业\n人孔作业\n高速公路施工\n基站天馈线安装": "A,B,C,D",
  "24. 根据文件1，通信建设工程安全生产费用的管理原则包括哪些？ (多选题)\n筹措有章\n支出有据\n管理有序\n监督有效": "A,B,C,D",
  "25. 根据文件2，以下哪些是人孔作业时必须采取的措施？ (多选题)\n配备气体检测仪\n设置安全警示标志\n作业人员佩戴防毒面具\n作业现场设置专人监护": "A,B,C,D",
  "26. 根据文件1，建设单位的安全生产责任包括哪些？ (多选题)\n建立健全安全生产规章制度\n制定生产安全事故应急救援预案\n每年至少组织一次应急演练\n不得对施工单位提出违反安全生产法规的要求": "A,B,C,D",
  "27. 根据文件2，以下哪些是移动基站天馈线安装作业时必须采取的措施？ (多选题)\n使用防坠落自锁装置\n设置施工禁区\n上下塔时按规定路由攀登\n传递工具时使用绳索": "A,B,C,D",
  "28. 根据文件2，以下哪些是综合布线系统工程作业现场的危险源？ (多选题)\n建筑工地的施工机械\n无扶手的楼梯\n开槽切割时的碎屑飞溅物\n天花板内绝缘破损的电源线": "A,B,C,D",
  "29. 根据文件1，施工单位的安全生产教育培训应包括哪些内容？ (多选题)\n安全生产知识\n安全生产规章制度\n安全操作技能\n事故应急处理措施": "A,B,C,D",
  "30. 根据文件2，以下哪些是架空线路作业时必须采取的措施？ (多选题)\n作业前检查杆根是否牢固\n使用合格的登高工具\n系好安全带\n杆下设置专人监护": "A,B,C,D",
  "31. 根据《判定标准》，以下哪些情形属于重大事故隐患？ (多选题)\n施工单位未按规定提取安全生产费用\n未对施工人员进行安全生产教育培训\n未按规定设置安全警示标识\n特种作业人员未持有效资格证书上岗": "A,B,C,D",
  "32. 根据文件2，以下哪些是设备安装作业时必须采取的措施？ (多选题)\n制定防静电措施\n使用绝缘工具\n作业前检查电源线\n作业区域设置防护栏": "A,B,C,D",
  "33. 根据文件1，通信建设工程安全生产工作的方针包括哪些？ (多选题)\n安全第一\n预防为主\n综合治理\n质量至上": "A,B,C",
  "34. 根据文件2，以下哪些是有限空间作业时必须配备的装备？ (多选题)\n气体检测仪\n通风设备\n安全警示标志\n个人防护装备": "A,B,C,D",
  "35. 根据《判定标准》，以下哪些行为属于重大事故隐患？ (多选题)\n未按规定对有限空间作业进行审批\n作业现场未设置专门人员进行安全管理\n未配置合格的安全防护装备\n特种作业人员未持有效资格证书上岗": "A,B,C,D",
  "36. 根据文件2，以下哪些是高速公路施工时必须遵守的规定？ (多选题)\n施工前书面报公路管理部门和公安交通管理部门\n作业人员必须穿着反光背心\n施工车辆必须停靠在指定区域\n作业时间必须在批准的时间内": "A,B,C,D",
  "37. 根据文件1，施工单位的安全生产费用应当用于哪些方面？ (多选题)\n完善安全生产条件\n改进安全生产条件\n购置安全防护装备\n安全生产培训": "A,B,C,D",
  "38. 重大危险源安全监测至少应包含哪些内容？ (多选题)\n危险物质温度\n安全阀启闭状态\n操作人员数量\n储罐液位": "A,B,D",
  "39. 安全评价机构的违法行为包括？ (多选题)\n超资质范围承揽业务\n未按规定公开评价报告\n评价人员同时在两家机构执业\n未按时提交年度总结": "A,B,C",
  "40. 工伤保险待遇包含？ (多选题)\n停工留薪期工资\n伤残辅助器具费用\n精神损害赔偿\n医疗期间交通补贴": "A,B,D",
  "41. 安全生产举报受理范围包括？ (多选题)\n瞒报生产安全事故\n强令冒险作业\n安全培训记录造假\n工程质量缺陷": "A,B,C",
  "42. 双重预防机制建设必须包含？ (多选题)\n风险分级管控清单\n隐患治理台账\n安全绩效考核方案\n应急资源分布图": "A,B",
  "43. 建设单位不得明示或暗示施工单位？ (多选题)\n使用不合格材料\n压缩合理工期\n降低安全施工条件\n增加监理巡查频次": "B,C",
  "44. 重大事故隐患判定标准涉及？ (多选题)\n涉及人员密集场所\n危化品超量存储\n特种设备未定期检验\n安全管理人员缺岗": "A,B,C",
  "45. 安全生产行政强制措施包括？ (多选题)\n查封违法设备\n责令停产停业\n冻结银行账户\n暂扣安全生产许可证": "A,B,D",
  "46. 安全标准化评审扣分项包括？ (多选题)\n未开展班组安全活动\n劳保用品发放延迟3天\n应急预案未向社区备案\n风险告知卡未上墙": "A,C,D",
  "47. 建设项目安全条件论证内容含？ (多选题)\n自然灾害影响\n周边环境敏感点\n施工队伍资质\n工艺技术成熟度": "A,B",
  "48. 重大事故隐患判据包括？ (多选题)\n危险物品存量超临界量\n安全间距不足法定值50%\n未建立双重预防机制\n特种作业无证上岗率≥20%": "A,B,D",
  "49. 安全生产刑事犯罪涉及？ (多选题)\n强令违章冒险作业罪\n重大劳动安全事故罪\n伪造检测数据罪\n挪用安全资金罪": "A,B,C,D",
  "50. 安全生产费用禁止用于？ (多选题)\n员工防暑降温饮料\n新建项目可研编制\n办公楼消防改造\n管理人员安全奖金": "A,B,C",
  "51. 5G基站AAU安装需特别检查的安全要素包括？ (多选题)\n抱杆抗风等级\n防雷接地电阻\n电磁辐射防护\n光缆最小弯曲半径": "A,B,C,D",
  "52. 有限空间救援装备必须包含？ (多选题)\n四合一气体检测仪\n正压式空气呼吸器\n三脚架救援系统\n防爆对讲机": "A,B,C,D",
  "53. 通信设备加电测试安全流程包括？ (多选题)\n验电笔检测断电\n逐级上电观察\n绝缘电阻测试\n防静电手腕接地": "A,B,C,D",
  "54. 光缆盘搬运机械伤害防范措施？ (多选题)\n使用专用提升架\n佩戴防切割手套\n盘缆半径≥20倍缆径\n夜间反光标识": "A,B,D",
  "55. 防雷系统检测必测参数？ (多选题)\n接地电阻值\n接闪器高度\n等电位连接电阻\nSPD漏电流值": "A,C,D",
  "56. 带电操作绝缘工具检查要点？ (多选题)\n有效期内试验合格证\n表面无龟裂破损\n湿度≤80%时使用\n双人确认绝缘等级": "A,B,D",
  "57. 有限空间作业\"四个一律\"要求？ (多选题)\n未经检测一律不得进入\n无监护人员一律停止作业\n未佩戴呼吸器一律处罚\n超时作业一律断电": "A,B",
  "58. 电缆沟施工有毒气体防控要求？ (多选题)\n强制通风30分钟以上\n四合一气体检测仪连续监测\n备用长管呼吸器\n设置气体捕集装置": "A,B,C",
  "59. 建设单位项目安全责任包括？ (多选题)\n审查施工组织设计中安全措施\n定期组织参建单位联合检查\n直接指挥施工单位隐患排查\n支付工伤保险费用": "A,B",
  "60. 安全生产协议必须明确？ (多选题)\n事故责任划分标准\n交叉作业协调机制\n安全考核奖惩细则\n工程款支付节点": "A,B,C",
  "61. 项目安全考核\"一票否决\"情形是？ (多选题)\n发生较大生产安全事故\n未通过安全生产标准化评审\n重大隐患逾期未整改\n安全费用支付不足80%": "A,C",
  "62. 建设单位需组织专家论证的情形包括？ (多选题)\n深基坑设计变更\n采用新型爬架施工工艺\n项目总投资增加30%\n毗邻高压输电线路施工": "A,B,D",
  "63. 项目安全生产责任保险必须覆盖？ (多选题)\n施工人员意外伤害\n第三者人身财产损失\n应急救援费用\n工程质量缺陷损失": "A,B,C\n判断题",
  "1. 生产经营单位的主要负责人对本单位的安全生产工作全面负责。 (判断题)\n正确\n错误": "正确",
  "2. 施工单位的主要负责人不需要具备安全生产知识和管理能力。 (判断题)\n正确\n错误": "错误",
  "3. 施工单位应为从业人员提供符合国家标准或行业标准的劳动防护用品。 (判断题)\n正确\n错误": "正确",
  "4. 根据《通信建设工程安全生产管理规定》，施工单位应为从业人员购买工伤保险。 (判断题)\n正确\n错误": "正确",
  "5. 施工单位在施工现场应配备必要的消防器材。 (判断题)\n正确\n错误": "正确",
  "6. 根据《通信建设工程安全生产管理规定》，施工单位应定期组织应急演练。 (判断题)\n正确\n错误": "正确",
  "7. 施工单位应为从业人员提供安全生产法律法规培训。 (判断题)\n正确\n错误": "正确",
  "8. 施工单位在施工现场应有专人负责安全监督。 (判断题)\n正确\n错误": "正确",
  "9. 根据《通信建设工程安全生产管理规定》，施工单位应为从业人员提供意外伤害保险。 (判断题)\n正确\n错误": "正确",
  "10. 施工单位应定期检查和维护施工现场的电气设备。 (判断题)\n正确\n错误": "正确",
  "11. 施工单位在高处作业时，施工人员必须佩戴安全带。 (判断题)\n正确\n错误": "正确",
  "12. 根据《通信建设工程安全生产管理规定》，施工单位应建立安全生产责任制。 (判断题)\n正确\n错误": "正确",
  "13. 施工单位应为从业人员提供免费的劳动防护用品。 (判断题)\n正确\n错误": "正确",
  "14. 施工单位在施工现场应设置明显的安全警示标志。 (判断题)\n正确\n错误": "正确",
  "15. 根据《通信建设工程安全生产管理规定》，施工单位应为从业人员购买商业保险。 (判断题)\n正确\n错误": "错误",
  "16. 施工单位在施工现场应确保高处作业有专人监护。 (判断题)\n正确\n错误": "正确",
  "17. 根据《通信建设工程安全生产管理规定》，施工单位应为从业人员提供安全帽、安全带等劳动防护用品。 (判断题)\n正确\n错误": "正确",
  "18. 施工单位在施工现场应确保电气设备接地。 (判断题)\n正确\n错误": "正确",
  "19. 施工单位在施工现场可以不采取防火措施进行动火作业。 (判断题)\n正确\n错误": "错误",
  "20. 根据《通信建设工程安全生产管理规定》，施工单位应定期组织安全生产教育培训。 (判断题)\n正确\n错误": "正确",
  "21. 施工单位在施工现场应确保电气设备有短路保护。 (判断题)\n正确\n错误": "正确",
  "22. 根据文件2，在高速公路施工时，必须设置安全警示标志。 (判断题)\n正确\n错误": "正确",
  "23. 根据文件1，建设单位应在工程开工后一个月内支付至少50%的安全生产费用。 (判断题)\n正确\n错误": "正确",
  "24. 生产经营单位的主要负责人对本单位安全生产工作全面负责。 (判断题)\n正确\n错误": "正确",
  "25. 安全生产\"三同时\"制度应在可行性研究阶段实施。 (判断题)\n正确\n错误": "正确",
  "26. 特种作业人员复审培训时间不得少于8学时。 (判断题)\n正确\n错误": "正确",
  "27. 建设单位有权要求施工单位提前完成合同约定的工期。 (判断题)\n正确\n错误": "错误",
  "28. 重大事故隐患治理方案应包含治理目标和任务。 (判断题)\n正确\n错误": "正确",
  "29. 工伤认定申请必须在事故发生后30日内提出。 (判断题)\n正确\n错误": "错误",
  "30. 项目专职安全员可同时负责两个工程项目。 (判断题)\n正确\n错误": "错误",
  "31. 事故调查组有权扣押相关企业的财务账册。 (判断题)\n正确\n错误": "正确",
  "32. 建设单位项目负责人对工程质量承担终身责任。 (判断题)\n正确\n错误": "正确",
  "33. 三级安全教育总学时不得少于24学时。 (判断题)\n正确\n错误": "正确",
  "34. 光缆接续作业允许在雨天进行，但需做好防雨措施。 (判断题)\n正确\n错误": "错误",
  "35. 有限空间作业前，氧气浓度检测值在19.5%-23.5%即为合格。 (判断题)\n正确\n错误": "正确",
  "36. 防雷接地电阻测试仪校准周期不得超过12个月。 (判断题)\n正确\n错误": "正确",
  "37. 带电操作必须使用绝缘等级为1000V以上的工具。 (判断题)\n正确\n错误": "错误",
  "38. 高空作业人员体重超过100kg时，应使用特制安全带。 (判断题)\n正确\n错误": "正确",
  "39. 施工临时用电系统允许采用\"一闸多机\"接线方式。 (判断题)\n正确\n错误": "错误",
  "40. 安全绳使用寿命自生产日期起计算，最长不超过5年。 (判断题)\n正确\n错误": "错误",
  "41. 手持式电动工具绝缘电阻检测周期为每季度一次。 (判断题)\n正确\n错误": "错误",
  "42. 通信铁塔垂直度偏差允许值为塔高的1/1500。 (判断题)\n正确\n错误": "正确",
  "43. 有毒气体检测仪报警值设定应低于国家职业接触限值的50%。 (判断题)\n正确\n错误": "正确",
  "44. 有限空间作业监护人可同时监管2个相邻作业点。 (判断题)\n正确\n错误": "错误",
  "45. 建设单位项目负责人对工程安全承担终身责任。 (判断题)\n正确\n错误": "正确",
  "46. 建设单位可要求施工单位将安全费用用于工程垫资。 (判断题)\n正确\n错误": "错误",
  "47. 监理单位下发停工令需经建设单位签字确认后方可执行。 (判断题)\n正确\n错误": "错误",
  "48. 建设单位安全总监必须持有注册安全工程师资格证书。 (判断题)\n正确\n错误": "正确",
  "49. 安全生产协议中可约定事故赔偿金额上限。 (判断题)\n正确\n错误": "错误",
  "50. 安全风险抵押金应在项目竣工验收后全额退还。 (判断题)\n正确\n错误": "错误",
  "51. 建设单位有权直接处罚施工单位的违章作业人员。 (判断题)\n正确\n错误": "错误",
  "52. 项目安全考核结果应作为工程款支付进度依据。 (判断题)\n正确\n错误": "正确",
  "53. 建设单位可委托监理单位代签安全技术交底文件。 (判断题)\n正确\n错误": "错误",
  "54. 危大工程专项施工方案需经建设单位项目负责人签字批准。 (判断题)\n正确\n错误": "错误",
  "55. 建设单位月度安全检查必须留存影像记录。 (判断题)\n正确\n错误": "正确",
  "56. 建设单位项目安全管理人员可同时兼任质量管理部门职务。 (判断题)\n正确\n错误": "错误"
}